cdm/__init__.py
cdm/cdm.py
cdm/ftypes.py
cdm/queue.py
cdm/utils.py
cdm-0.1.17.dist-info/LICENSE
cdm-0.1.17.dist-info/METADATA
cdm-0.1.17.dist-info/WHEEL
cdm-0.1.17.dist-info/entry_points.txt
cdm-0.1.17.dist-info/top_level.txt
cdm-0.1.17.dist-info/RECORD
