Metadata-Version: 2.1
Name: cdm
Version: 0.1.17
Summary: Charzeh Download Manager
Home-page: https://github.com/amirmd76/cdm.git
Author: AmirMohammad Dehghan
Author-email: amirmd76@gmail.com
License: MIT
License-File: LICENSE
